CHANGES.txt
COPYRIGHT.txt
LICENSE.txt
MANIFEST.in
README.txt
bootstrap.py
buildout.cfg
setup.py
src/tranchitella/__init__.py
src/tranchitella.recipe.wsgi.egg-info/PKG-INFO
src/tranchitella.recipe.wsgi.egg-info/SOURCES.txt
src/tranchitella.recipe.wsgi.egg-info/dependency_links.txt
src/tranchitella.recipe.wsgi.egg-info/entry_points.txt
src/tranchitella.recipe.wsgi.egg-info/namespace_packages.txt
src/tranchitella.recipe.wsgi.egg-info/not-zip-safe
src/tranchitella.recipe.wsgi.egg-info/requires.txt
src/tranchitella.recipe.wsgi.egg-info/top_level.txt
src/tranchitella/recipe/__init__.py
src/tranchitella/recipe/wsgi/__init__.py
src/tranchitella/recipe/wsgi/recipe.txt
src/tranchitella/recipe/wsgi/tests.py