Metadata-Version: 1.0
Name: tranchitella.recipe.wsgi
Version: 0.4
Summary: Buildout recipe to create paste.deploy entry points for mod_wsgi
Home-page: http://pypi.python.org/pypi/tranchitella.recipe.wsgi
Author: Tranchitella Kft.
Author-email: info@tranchitella.eu
License: GPL 2
Platform: UNKNOWN
Classifier: Framework :: Buildout
Classifier: Intended Audience :: Developers
Classifier: Intended Audience :: System Administrators
Classifier: License :: OSI Approved :: GNU General Public License (GPL)
Classifier: Programming Language :: Python
